{
    "common": {
        "name": "eusec",
        "version": "0.8.4",
        "news": {
            "0.8.4": {
                "en": "Updated version of the package eufy-security-client (1.6.5)\nFixed issue #228",
                "de": "Version des Pakets eufy-security-client (1.6.5) aktualisiert\nProblem #228 behoben",
                "ru": "Обновленная версия пакета eufy-security-client (1.6.5)\nИсправлена проблема №228",
                "pt": "Versão atualizada do pacote eufy-security-client (1.6.5)\nEdição fixa #228",
                "nl": "Bijgewerkte versie van het pakket eufy-security-client (1.6.5)\nProbleem #228 opgelost",
                "fr": "Version mise à jour du paquet eufy-security-client (1.6.5)\nCorrection du problème n°228",
                "it": "Aggiornata la versione del pacchetto eufy-security-client (1.6.5)\nRisolto il problema #228",
                "es": "Versión actualizada del paquete eufy-security-client (1.6.5)\nCorregido el problema #228",
                "pl": "Zaktualizowana wersja pakietu eufy-security-client (1.6.5)\nNaprawiono błąd #228",
                "zh-cn": "包 eufy-security-client (1.6.5) 的更新版本\n修正了问题#228"
            },
            "0.8.3": {
                "en": "Updated version of the package eufy-security-client (1.6.4)\nFixed issue #222",
                "de": "Version des Pakets eufy-security-client (1.6.4) aktualisiert\nProblem #222 behoben",
                "ru": "Обновленная версия пакета eufy-security-client (1.6.4)\nИсправлена проблема №222",
                "pt": "Versão atualizada do pacote eufy-security-client (1.6.4)\nEdição fixa #222",
                "nl": "Bijgewerkte versie van het pakket eufy-security-client (1.6.4)\nProbleem #222 opgelost",
                "fr": "Version mise à jour du paquet eufy-security-client (1.6.4)\nCorrection du problème n°222",
                "it": "Aggiornata la versione del pacchetto eufy-security-client (1.6.4)\nRisolto il problema #222",
                "es": "Versión actualizada del paquete eufy-security-client (1.6.4)\nCorregido el problema #222",
                "pl": "Zaktualizowana wersja pakietu eufy-security-client (1.6.4)\nNaprawiono błąd #222",
                "zh-cn": "包 eufy-security-client (1.6.4) 的更新版本\n修正了问题#222"
            },
            "0.8.2": {
                "en": "Renamed Adapter to ioBroker.euSec\nUpdated version of the package eufy-security-client (1.6.3)\nFixed issue #221",
                "de": "Umbenennung des Adapters in ioBroker.euSec\nVersion des Pakets eufy-security-client (1.6.3) aktualisiert\nProblem #221 behoben",
                "ru": "Переименовать адаптер в ioBroker.euSec\nОбновленная версия пакета eufy-security-client (1.6.3)\nИсправлена проблема №221",
                "pt": "Renomeado Adaptador para ioBroker.euSec\nVersão atualizada do pacote eufy-security-client (1.6.3)\nEdição fixa #221",
                "nl": "Adapter hernoemd naar ioBroker.euSec\nBijgewerkte versie van het pakket eufy-security-client (1.6.3)\nProbleem #221 opgelost",
                "fr": "Renommé Adaptateur à ioBroker.euSec\nVersion mise à jour du paquet eufy-security-client (1.6.3)\nCorrection du problème n°221",
                "it": "Rinominato adattatore in ioBroker.euSec\nAggiornata la versione del pacchetto eufy-security-client (1.6.3)\nRisolto il problema #221",
                "es": "Cambio de nombre del adaptador a ioBroker.euSec\nVersión actualizada del paquete eufy-security-client (1.6.3)\nCorregido el problema #221",
                "pl": "Zmiana nazwy adaptera na ioBroker.euSec\nZaktualizowana wersja pakietu eufy-security-client (1.6.3)\nNaprawiono błąd #221",
                "zh-cn": "重新命名适配器为ioBroker.euSec\n包 eufy-security-client (1.6.3) 的更新版本\n修正了问题#221"
            },
            "0.8.1": {
                "en": "Updated version of the package eufy-security-client (1.6.2)\nFixed issue #219",
                "de": "Version des Pakets eufy-security-client (1.6.2) aktualisiert\nProblem #219 behoben",
                "ru": "Обновленная версия пакета eufy-security-client (1.6.2)\nИсправлена проблема №219",
                "pt": "Versão atualizada do pacote eufy-security-client (1.6.2)\nEdição fixa #219",
                "nl": "Bijgewerkte versie van het pakket eufy-security-client (1.6.2)\nProbleem #219 opgelost",
                "fr": "Version mise à jour du paquet eufy-security-client (1.6.2)\nCorrection du problème n°219",
                "it": "Aggiornata la versione del pacchetto eufy-security-client (1.6.2)\nRisolto il problema #219",
                "es": "Versión actualizada del paquete eufy-security-client (1.6.2)\nCorregido el problema #219",
                "pl": "Zaktualizowana wersja pakietu eufy-security-client (1.6.2)\nNaprawiono błąd #219",
                "zh-cn": "包 eufy-security-client (1.6.2) 的更新版本\n修正了问题#219"
            },
            "0.8.0": {
                "en": "Updated version of the package eufy-security-client (1.6.1)\nAdded support for Smart Lock Touch & Wifi (T8520)\nAdded option to enable/disable \"Automatically download video\"\nAdded new state to retrieve received captcha in HTML format \"received_captcha_html\"\nFixed issue #199\nFixed issue #217",
                "de": "Version des Pakets eufy-security-client (1.6.1) aktualisiert\nUnterstützung für Smart Lock Touch & Wifi hinzugefügt (T8520)\nOption zum Aktivieren/Deaktivieren von \"Automatisches Herunterladen von Videos\" hinzugefügt\nNeuer Status hinzugefügt, um empfangene Captcha im HTML-Format abzurufen \"received_captcha_html\"\nProblem #199 behoben\nProblem #217 behoben",
                "ru": "Обновленная версия пакета eufy-security-client (1.6.1)\nДобавлена поддержка Smart Lock Touch & Wifi (T8520)\nДобавлена опция включения/отключения \"Автоматическая загрузка видео\"\nДобавлено новое состояние для получения полученной капчи в формате HTML \"received_captcha_html\"\nИсправлена проблема #199\nИсправлена проблема №217",
                "pt": "Versão atualizada do pacote eufy-security-client (1.6.1)\nSuporte adicional para Smart Lock Touch & Wifi (T8520)\nOpção adicional para activar/desactivar \"Descarregar vídeo automaticamente\".\nAdicionado novo estado para recuperar captcha recebida em formato HTML \"received_captcha_html\"\nEdição fixa #199\nEdição fixa #217",
                "nl": "Bijgewerkte versie van het pakket eufy-security-client (1.6.1)\nOndersteuning toegevoegd voor Smart Lock Touch & Wifi (T8520)\nOptie toegevoegd om \"Video automatisch downloaden\" in/uit te schakelen\nNieuwe status toegevoegd om ontvangen captcha op te halen in HTML formaat \"received_captcha_html\"\nProbleem #199 opgelost\nProbleem #217 opgelost",
                "fr": "Version mise à jour du paquet eufy-security-client (1.6.1)\nAjout d'un support pour Smart Lock Touch & Wifi (T8520)\nAjout d'une option pour activer/désactiver \"Téléchargement automatique de la vidéo\".\nAjout d'un nouvel état pour récupérer le captcha reçu au format HTML \"received_captcha_html\".\nCorrection du problème #199\nCorrection du problème n°217",
                "it": "Aggiornata la versione del pacchetto eufy-security-client (1.6.1)\nAggiunto il supporto per Smart Lock Touch & Wifi (T8520)\nAggiunta opzione per abilitare/disabilitare \"Scarica automaticamente il video\".\nAggiunto un nuovo stato per recuperare i captcha ricevuti in formato HTML \"received_captcha_html\".\nRisolto il problema #199\nRisolto il problema #217",
                "es": "Versión actualizada del paquete eufy-security-client (1.6.1)\nAñadido soporte para Smart Lock Touch y Wifi (T8520)\nAñadida la opción de activar/desactivar \"Descarga automática de vídeo\"\nAñadido un nuevo estado para recuperar el captcha recibido en formato HTML \"received_captcha_html\"\nCorregido el problema #199\nCorregido el problema #217",
                "pl": "Zaktualizowana wersja pakietu eufy-security-client (1.6.1)\nDodano wsparcie dla Smart Lock Touch & Wifi (T8520)\nDodano możliwość włączenia/wyłączenia opcji \"Automatycznie pobieraj wideo\"\nDodano nowy stan, aby pobrać otrzymaną captcha w formacie HTML \"received_captcha_html\"\nNaprawiono błąd #199\nNaprawiono błąd #217",
                "zh-cn": "包 eufy-security-client (1.6.1) 的更新版本\n增加了对智能锁触摸和Wifi（T8520）的支持\n增加了启用/禁用 \"自动下载视频\" 的选项\n增加了新的状态来检索收到的HTML格式的验证码 \"received_captcha_html\"\n修正了问题#199\n修正了问题#217"
            },
            "0.7.5": {
                "en": "Fixed issue #195 and #202",
                "de": "Problem Nr. 195 und Nr. 202 behoben",
                "ru": "Исправлена проблема № 195 и № 202.",
                "pt": "Correção do problema nº 195 e nº 202",
                "nl": "Probleem #195 en #202 opgelost",
                "fr": "Problèmes résolus #195 et #202",
                "it": "Risolto il problema #195 e #202",
                "es": "Problema solucionado #195 y #202",
                "pl": "Naprawiono problem #195 i #202",
                "zh-cn": "修复了＃195和＃202问题"
            },
            "0.7.4": {
                "en": "Updated version of the package eufy-security-client (1.4.0)",
                "de": "Version des Pakets eufy-security-client (1.4.0) aktualisiert",
                "ru": "Обновленная версия пакета eufy-security-client (1.4.0)",
                "pt": "Versão atualizada do pacote eufy-security-client (1.4.0)",
                "nl": "Bijgewerkte versie van het pakket eufy-security-client (1.4.0)",
                "fr": "Version mise à jour du paquet eufy-security-client (1.4.0)",
                "it": "Aggiornata la versione del pacchetto eufy-security-client (1.4.0)",
                "es": "Versión actualizada del paquete eufy-security-client (1.4.0)",
                "pl": "Zaktualizowana wersja pakietu eufy-security-client (1.4.0)",
                "zh-cn": "包 eufy-security-client (1.4.0) 的更新版本"
            },
            "0.7.3": {
                "en": "Updated version of the package eufy-security-client (1.3.0)",
                "de": "Version des Pakets eufy-security-client (1.3.0) aktualisiert",
                "ru": "Обновленная версия пакета eufy-security-client (1.3.0)",
                "pt": "Versão atualizada do pacote eufy-security-client (1.3.0)",
                "nl": "Bijgewerkte versie van het pakket eufy-security-client (1.3.0)",
                "fr": "Version mise à jour du paquet eufy-security-client (1.3.0)",
                "it": "Aggiornata la versione del pacchetto eufy-security-client (1.3.0)",
                "es": "Versión actualizada del paquete eufy-security-client (1.3.0)",
                "pl": "Zaktualizowana wersja pakietu eufy-security-client (1.3.0)",
                "zh-cn": "包 eufy-security-client (1.3.0) 的更新版本"
            },
            "0.7.2": {
                "en": "Updated version of the package eufy-security-client (1.2.3)",
                "de": "Version des Pakets eufy-security-client (1.2.3) aktualisiert",
                "ru": "Обновленная версия пакета eufy-security-client (1.2.3)",
                "pt": "Versão atualizada do pacote eufy-security-client (1.2.3)",
                "nl": "Bijgewerkte versie van het pakket eufy-security-client (1.2.3)",
                "fr": "Version mise à jour du paquet eufy-security-client (1.2.3)",
                "it": "Aggiornata la versione del pacchetto eufy-security-client (1.2.3)",
                "es": "Versión actualizada del paquete eufy-security-client (1.2.3)",
                "pl": "Zaktualizowana wersja pakietu eufy-security-client (1.2.3)",
                "zh-cn": "包 eufy-security-client (1.2.3) 的更新版本"
            }
        },
        "title": "euSec",
        "titleLang": {
            "en": "euSec",
            "de": "euSec",
            "ru": "euSec",
            "pt": "euSec",
            "nl": "euSec",
            "fr": "euSec",
            "it": "euSec",
            "es": "euSec",
            "pl": "euSec",
            "zh-cn": "euSec"
        },
        "desc": {
            "en": "Support for Eufy-Security cameras with stations",
            "de": "Unterstützung für Eufy-Security-Kameras mit Stationen",
            "ru": "Поддержка камер Eufy-Security со станциями",
            "pt": "Suporte para câmeras de segurança Eufy com estações",
            "nl": "Ondersteuning voor Eufy-Security-camera's met stations",
            "fr": "Prise en charge des caméras Eufy-Security avec stations",
            "it": "Supporto per telecamere Eufy-Security con stazioni",
            "es": "Soporte para cámaras Eufy-Security con estaciones",
            "pl": "Wsparcie dla kamer Eufy-Security ze stacjami",
            "zh-cn": "支持带站的Eufy-Security摄像机"
        },
        "authors": [
            "bropat <patrick.broetto@gmail.com>"
        ],
        "keywords": [
            "eufy",
            "eufycam",
            "cam",
            "cameras",
            "security",
            "doorbell",
            "eufy-security",
            "iobroker"
        ],
        "license": "MIT",
        "platform": "Javascript/Node.js",
        "main": "build/main.js",
        "icon": "eusec.png",
        "enabled": true,
        "extIcon": "https://raw.githubusercontent.com/bropat/ioBroker.eusec/master/admin/eusec.png",
        "readme": "https://github.com/bropat/ioBroker.eusec/blob/master/README.md",
        "loglevel": "info",
        "mode": "daemon",
        "type": "alarm",
        "compact": true,
        "connectionType": "cloud",
        "dataSource": "poll",
        "materialize": true,
        "webExtension": "build/lib/web.js",
        "dependencies": [
            {
                "js-controller": ">=3.1.4",
                "web": ">=2.0.0"
            }
        ],
        "globalDependencies": [
            {
                "admin": ">=4.0.10"
            }
        ],
        "dataFolder": "eusec.%INSTANCE%",
        "jsonConfig": true,
        "adminUI": {
            "config": "json"
        }
    },
    "encryptedNative": [
        "password"
    ],
    "protectedNative": [
        "password"
    ],
    "native": {
        "username": "",
        "password": "",
        "pollingInterval": 10,
        "maxLivestreamDuration": 120,
        "verificationMethod": 2,
        "eventDuration": 15,
        "webInstance": "*",
        "p2pConnectionType": "quickest",
        "acceptInvitations": true,
        "alarmSoundDuration": 60,
        "autoDownloadVideo": false
    },
    "objects": [],
    "instanceObjects": [
        {
            "_id": "",
            "type": "meta",
            "common": {
              "name": "User files for euSec",
              "type": "meta.user"
            },
            "native": {}
        }
    ]
}